README.md
setup.cfg
setup.py
rnadecoder/__init__.py
rnadecoder/rnadecoder.py
rnadecoder.egg-info/PKG-INFO
rnadecoder.egg-info/SOURCES.txt
rnadecoder.egg-info/dependency_links.txt
rnadecoder.egg-info/top_level.txt